[
  {
    "site": "all-armatura.ru",
    "inn": "7811710501"
  },
  {
    "site": "armaturka.ru",
    "inn": "7707419159"
  },
  {
    "site": "armatek.ru",
    "inn": "7804039762"
  },
  {
    "site": "npoasta.ru",
    "inn": "7817140745"
  },
  {
    "site": "armatura-optom.ru",
    "inn": "7733343925"
  },
  {
    "site": "arm-plast.ru",
    "inn": "5257157370"
  },
  {
    "site": "metallotorg.ru",
    "inn": "7118018781"
  },
  {
    "site": "armatura-mm.ru",
    "inn": "7707419159"
  },
  {
    "site": "stroymetall.ru",
    "inn": "7804547903"
  },
  {
    "site": "termoros.com",
    "inn": "7728604924"
  },
  {
    "site": "rzta.ru",
    "inn": "7606094264"
  }
]